HackDuck/__init__.py
HackDuck/main.py
HackDuck-0.1.5.data/scripts/hackduck
HackDuck-0.1.5.dist-info/LICENCE
HackDuck-0.1.5.dist-info/METADATA
HackDuck-0.1.5.dist-info/WHEEL
HackDuck-0.1.5.dist-info/top_level.txt
HackDuck-0.1.5.dist-info/RECORD
