Metadata-Version: 2.1
Name: HackDuck
Version: 0.1.5
Summary: Machine learning data flow for reproducible data science
Home-page: https://github.com/AlexandreKempf/HackDuck
Author: Alexandre Kempf
Author-email: alexandre.kempf@cri-paris.org
License: UNKNOWN
Platform: UNKNOWN
Classifier: Programming Language :: Python :: 3
Classifier: License :: OSI Approved :: MIT License
Classifier: Operating System :: OS Independent
Requires-Python: >=3.6
Requires-Dist: prefect
Requires-Dist: mlflow
Requires-Dist: pyyaml
Requires-Dist: numpy
Requires-Dist: torch
Requires-Dist: simplejson
Requires-Dist: TaskBank
